magic_scissors/__init__.py
magic_scissors/generate_image.py
magic_scissors/magic_scissors.py
magic_scissors-0.1.0.dist-info/METADATA
magic_scissors-0.1.0.dist-info/WHEEL
magic_scissors-0.1.0.dist-info/top_level.txt
magic_scissors-0.1.0.dist-info/RECORD
